mgit/__init__.py
mgit/cli.py
mgit/git.py
mgit-1.3.0.dist-info/LICENSE
mgit-1.3.0.dist-info/METADATA
mgit-1.3.0.dist-info/WHEEL
mgit-1.3.0.dist-info/entry_points.txt
mgit-1.3.0.dist-info/top_level.txt
mgit-1.3.0.dist-info/RECORD
