Metadata-Version: 2.1
Name: mgit
Version: 1.3.0
Summary: Fetch collections of git projects
Home-page: https://github.com/zsimic/mgit
Author: Zoran Simic
Author-email: zoran@simicweb.com
License: MIT
Keywords: multiple,git,repos
Platform: UNKNOWN
Classifier: Development Status :: 4 - Beta
Classifier: Environment :: Console
Classifier: Intended Audience :: Developers
Classifier: Operating System :: MacOS :: MacOS X
Classifier: Operating System :: POSIX
Classifier: Operating System :: Unix
Classifier: Programming Language :: Python
Classifier: Programming Language :: Python :: 3
Classifier: Programming Language :: Python :: 3.6
Classifier: Programming Language :: Python :: 3.7
Classifier: Programming Language :: Python :: 3.8
Classifier: Programming Language :: Python :: 3.9
Classifier: Programming Language :: Python :: Implementation :: CPython
Classifier: Topic :: Software Development :: Build Tools
Classifier: Topic :: Utilities
Requires-Python: >=3.6
License-File: LICENSE
Requires-Dist: click (==8.0.1)
Requires-Dist: runez (==2.7.4)
